[
  {
    "id": "sea_1",
    "title": "3D Ocean Waves",
    "description": "Calm 3D ocean waves",
    "type": "image",
    "source": "https://images.unsplash.com/photo-1505142468610-359e7d316be0?w=1920&h=1080&fit=crop",
    "category": "sea",
    "isBuiltIn": true
  },
  {
    "id": "sea_2",
    "title": "3D Underwater Scene",
    "description": "Beautiful 3D underwater world",
    "type": "image",
    "source": "https://images.unsplash.com/photo-1506905925346-21bda4d32df4?w=1920&h=1080&fit=crop",
    "category": "sea",
    "isBuiltIn": true
  },
  {
    "id": "sea_3",
    "title": "3D Beach Sunset",
    "description": "Stunning 3D beach at sunset",
    "type": "image",
    "source": "https://images.unsplash.com/photo-1505142468610-359e7d316be0?w=1920&h=1080&fit=crop",
    "category": "sea",
    "isBuiltIn": true
  },
  {
    "id": "sea_4",
    "title": "3D Coastal Cliffs",
    "description": "Dramatic 3D coastal cliffs",
    "type": "image",
    "source": "https://images.unsplash.com/photo-1505142468610-359e7d316be0?w=1920&h=1080&fit=crop",
    "category": "sea",
    "isBuiltIn": true
  },
  {
    "id": "sea_5",
    "title": "3D Tropical Paradise",
    "description": "Beautiful 3D tropical sea",
    "type": "image",
    "source": "https://images.unsplash.com/photo-1505142468610-359e7d316be0?w=1920&h=1080&fit=crop",
    "category": "sea",
    "isBuiltIn": true
  },
  {
    "id": "sea_6",
    "title": "3D Ocean Depth",
    "description": "Mysterious 3D deep ocean",
    "type": "image",
    "source": "https://images.unsplash.com/photo-1505142468610-359e7d316be0?w=1920&h=1080&fit=crop",
    "category": "sea",
    "isBuiltIn": true
  }
]

